pycollision/__init__.py
pycollision/pycollision.py
PyCollision-0.0.2.dist-info/LICENSE.txt
PyCollision-0.0.2.dist-info/METADATA
PyCollision-0.0.2.dist-info/WHEEL
PyCollision-0.0.2.dist-info/top_level.txt
PyCollision-0.0.2.dist-info/RECORD
