Metadata-Version: 2.1
Name: PyCollision
Version: 0.0.2
Summary: This library helps to detect collision for image with transparency. Useful for game development 
Home-page: https://github.com/PaulleDemon/PyCollision
Author: Paul
License: MIT
Keywords: Collision,pygame,python collision,Rectangular collision,pycollision
Platform: UNKNOWN
Classifier: License :: OSI Approved :: MIT License
Classifier: Development Status :: 4 - Beta
Classifier: Programming Language :: Python :: 3.5
Classifier: Programming Language :: Python :: 3.6
Classifier: Programming Language :: Python :: 3.7
Classifier: Programming Language :: Python :: 3.8
Classifier: Programming Language :: Python :: 3.9
Classifier: Programming Language :: Python :: 3.10
Requires-Python: >=3.5
Requires-Dist: numpy
Requires-Dist: pillow
